[
  {
    "name": "कालिदास",
    "period": "गुप्त काल",
    "court": "चंद्रगुप्त-II के नवरत्न",
    "works": [
      { "title": "मालविकाग्निमित्रम्", "type": "नाटक" },
      { "title": "विक्रमोर्वशीयम्", "type": "नाटक" },
      { "title": "अभिज्ञानशाकुंतलम्", "type": "नाटक" },
      { "title": "ऋतुसंहार", "type": "खण्डकाव्य" },
      { "title": "मेघदूतम्", "type": "संदेशकाव्य" },
      { "title": "रघुवंशम्", "type": "महाकाव्य" },
      { "title": "कुमारसंभवम्", "type": "महाकाव्य" }
    ]
  },
  {
    "name": "विशाखदत्त",
    "period": "गुप्त काल",
    "works": [
      {
        "title": "मुद्राराक्षस",
        "type": "नाटक",
        "notes": "चंद्रगुप्त मौर्य के समय का राजदरबारी षड्यंत्र, चंद्रगुप्त को वृषल/कुलहीन कहा गया, ढूंढीराज की टीका"
      },
      {
        "title": "देवीचंद्रगुप्तम्",
        "type": "नाटक",
        "notes": "रामगुप्त का वर्णन, अब लुप्त"
      }
    ]
  },
  {
    "name": "शूद्रक",
    "period": "गुप्त काल",
    "works": [
      {
        "title": "मृच्छकटिकम्",
        "type": "नाटक",
        "notes": "मिट्टी की बैलगाड़ी, चारुदत्त और वसंतसेना की प्रेम कहानी"
      }
    ]
  },
  {
    "name": "विष्णु शर्मा",
    "period": "गुप्त काल",
    "works": [{ "title": "पंचतंत्र", "type": "नीति कथा संग्रह" }]
  },
  {
    "name": "नारायण पंडित",
    "works": [{ "title": "हितोपदेश", "type": "नीति कथा संग्रह" }]
  },
  {
    "name": "अश्वघोष",
    "court": "कनिष्क का दरबारी कवि",
    "works": [
      { "title": "बुद्धचरित", "type": "महाकाव्य" },
      { "title": "सौन्दरानन्द", "type": "काव्य" },
      { "title": "सारिपुत्र प्रकरण", "type": "नाटक" },
      { "title": "सूत्रालंकार", "type": "अलंकार ग्रंथ" },
      { "title": "वज्रसूची", "type": "जातिभेद निरर्थकता पर ग्रंथ" }
    ]
  },
  {
    "name": "नागार्जुन",
    "court": "कनिष्क का दरबारी",
    "works": [
      { "title": "माध्यमिक कारिका", "type": "दार्शनिक" },
      { "title": "प्रज्ञापारमिता सूत्र शास्त्र", "type": "बौद्ध दर्शन" }
    ]
  },
  {
    "name": "वसुमित्र",
    "court": "कनिष्क का दरबारी, चतुर्थ बौद्ध संगीति के अध्यक्ष",
    "works": [{ "title": "महाविभाष शास्त्र", "type": "बौद्ध विश्वकोश" }]
  },
  {
    "name": "भद्रबाहु",
    "notes": "दिगंबर जैन, चंद्रगुप्त मौर्य के गुरु",
    "works": [{ "title": "कल्पसूत्र", "type": "जैन ग्रंथ" }]
  },
  {
    "name": "बाणभट्ट",
    "court": "हर्षवर्धन का दरबारी",
    "works": [
      { "title": "कादंबरी", "type": "गद्य काव्य" },
      { "title": "हर्षचरित", "type": "जीवनी-काव्य" },
      { "title": "चंडी शतक", "type": "स्तोत्र" },
      { "title": "पार्वतीपरिणय", "type": "नाटक" }
    ]
  },
  {
    "name": "भास",
    "works": [
      { "title": "स्वप्नवासवदत्ता", "type": "नाटक" },
      { "title": "चारुदत्त", "type": "नाटक" },
      { "title": "दूतवाक्यम", "type": "एकांक नाटक" },
      { "title": "दूतघटोत्कचम्", "type": "एकांक नाटक" },
      { "title": "कर्णभारम्", "type": "एकांक नाटक" },
      { "title": "उरुभंगम्", "type": "एकांक नाटक (दुर्योधन)" },
      { "title": "मध्यम व्यायोग", "type": "व्यायोग नाटक (भीम)" },
      { "title": "पंचरात्र", "type": "नाटक" },
      { "title": "प्रतिज्ञायौगन्धरायणम्", "type": "नाटक" },
      { "title": "बालचरित", "type": "नाटक" },
      { "title": "प्रतिमा नाटक", "type": "नाटक" },
      { "title": "अभिषेक नाटक", "type": "नाटक" },
      { "title": "अविमारक", "type": "नाटक" }
    ]
  },
  {
    "name": "भवभूति",
    "court": "यशोवर्मन (कन्नौज) के दरबारी",
    "works": [
      { "title": "उत्तररामचरित", "type": "नाटक" },
      { "title": "मालती-माधव", "type": "नाटक" },
      { "title": "महावीरचरित", "type": "नाटक" }
    ]
  },
  {
    "name": "भारवी",
    "court": "पल्लव नरेश सिंहविष्णु के दरबारी",
    "works": [{ "title": "किरातार्जुनीयम्", "type": "महाकाव्य" }]
  },
  {
    "name": "नागसेन",
    "works": [{ "title": "मिलिंदपन्हो", "type": "पालि, प्रश्नोत्तर ग्रंथ" }]
  },
  {
    "name": "वराहमिहिर",
    "court": "चंद्रगुप्त-II के नवरत्न",
    "works": [
      { "title": "बृहत्संहिता", "type": "ज्योतिष-विज्ञान" },
      { "title": "बृहज्जातक", "type": "ज्योतिष" },
      { "title": "पंचसिद्धांतिका", "type": "खगोल ग्रंथ" }
    ]
  },
  {
    "name": "वररुचि",
    "court": "चंद्रगुप्त-II के नवरत्न",
    "works": [{ "title": "प्राकृतप्रकाश", "type": "प्राकृत व्याकरण" }]
  },
  {
    "name": "अमरसिंह",
    "court": "चंद्रगुप्त-II के नवरत्न",
    "works": [{ "title": "अमरकोश", "type": "कोश ग्रंथ" }]
  },
  {
    "name": "वाग्भट्ट",
    "court": "चंद्रगुप्त-II के नवरत्न",
    "works": [
      { "title": "अष्टांगहृदय", "type": "आयुर्वेद" },
      { "notes": "टीकाकार: हेमाद्रि" }
    ]
  },
  {
    "name": "पाणिनि",
    "period": "नंद काल",
    "works": [{ "title": "अष्टाध्यायी", "type": "संस्कृत व्याकरण" }]
  },
  {
    "name": "पतंजलि",
    "notes": "पुष्यमित्र शुंग के पुरोहित",
    "works": [
      { "title": "योगसूत्र", "type": "योग दर्शन" },
      { "title": "महाभाष्य", "type": "अष्टाध्यायी की महान टीका" }
    ]
  },
  {
    "name": "सर्ववर्मा",
    "period": "सातवाहन काल",
    "works": [{ "title": "कातन्त्र", "type": "संस्कृत व्याकरण (सरल)" }]
  },
  {
    "name": "यास्क",
    "works": [{ "title": "निरुक्त", "type": "वैदिक शब्द व्युत्पत्ति" }]
  },
  {
    "name": "हर्षवर्धन",
    "works": [
      { "title": "प्रियदर्शिका", "type": "नाटक" },
      { "title": "रत्नावली", "type": "नाटक" },
      { "title": "नागानंद", "type": "नाटक" }
    ]
  },
  {
    "name": "महेंद्रवर्मन प्रथम",
    "notes": "पल्लव शासक",
    "works": [{ "title": "मत्तविलास प्रहसन", "type": "प्रहसन (बौद्ध-कापालिक व्यंग्य)" }]
  },
  {
    "name": "आर्यभट्ट",
    "period": "गुप्त काल",
    "works": [
      { "title": "आर्यभटीय", "type": "गणित-खगोल" },
      { "title": "सूर्य सिद्धांत", "type": "खगोल (संशोधित)" }
    ]
  },
  {
    "name": "भास्कर प्रथम",
    "works": [
      { "title": "महाभास्करीय", "type": "खगोल" },
      { "title": "लघुभास्करीय", "type": "खगोल" },
      { "title": "आर्यभटीयभाष्य", "type": "टीका" }
    ]
  },
  {
    "name": "ब्रह्मगुप्त",
    "period": "गुप्त काल",
    "works": [
      { "title": "ब्रह्मस्फुटसिद्धांत", "type": "गणित-खगोल" },
      { "title": "खण्डखाद्यक", "type": "खगोल" }
    ]
  },
  {
    "name": "दंडी",
    "court": "पल्लव नरसिंहवर्मन-II के दरबारी",
    "works": [
      { "title": "दशकुमारचरित", "type": "गद्य काव्य" },
      { "title": "काव्यादर्श", "type": "अलंकार शास्त्र" }
    ]
  },
  {
    "name": "गुणाढ्य",
    "court": "सातवाहन हाल के दरबारी",
    "works": [{ "title": "बृहत्कथा", "type": "प्राकृत महाकाव्य (मूल)" }]
  },
  {
    "name": "क्षेमेंद्र",
    "period": "कश्मीर",
    "works": [{ "title": "बृहत्कथा मंजरी", "type": "संक्षेप" }]
  },
  {
    "name": "सोमदेव",
    "period": "11वीं सदी, कश्मीर",
    "works": [{ "title": "कथासरित्सागर", "type": "बृहत्कथा का सबसे बड़ा संकलन" }]
  },
  {
    "name": "कामंदक",
    "works": [{ "title": "नीतिसार", "type": "राजनीति शास्त्र" }]
  },
  {
    "name": "चरक",
    "court": "कनिष्क का दरबारी",
    "works": [{ "title": "चरक संहिता", "type": "आयुर्वेद" }]
  },
  {
    "name": "सुश्रुत",
    "period": "महाजनपद काल",
    "works": [{ "title": "सुश्रुत संहिता", "type": "शल्य चिकित्सा" }]
  },
  {
    "name": "वात्स्यायन",
    "works": [{ "title": "कामसूत्र", "type": "कामशास्त्र" }]
  },
  {
    "name": "तिरुवल्लुवर",
    "works": [{ "title": "तिरुक्कुरल (मुप्पाल)", "type": "तमिल नीति-दर्शन ग्रंथ" }]
  },
  {
    "name": "इलंगो अडिगल",
    "notes": "चोल राजा करिकाल का भाई",
    "works": [{ "title": "शिलप्पदिकारम", "type": "तमिल महाकाव्य" }]
  },
  {
    "name": "सीत्तलै सात्तनार",
    "works": [{ "title": "मणिमेखलै", "type": "तमिल महाकाव्य (बौद्ध)" }]
  },
  {
    "name": "अज्ञात यूनानी नाविक",
    "works": [{ "title": "पेरिप्लस ऑफ द एरिथ्रियन सी", "type": "यूनानी यात्रा वृत्तांत" }]
  }
]
